{
  "openFile.dropFileHere": "Glisser le document ici",
  "openFile.openFileDisabled": "Pas de document",
  "openFile.openDocument": "Ouvrir le document",
  "openFile.selectFile": "Sélectionner le fichier",
  "openFileError.description": "Le fichier n’a pas pu être ouvert",
  "openFileError.ok": "OK",
  "loadFile.title": "Chargement du fichier",
  "saveFile.title": "Le fichier est sauvegardé",
  "passwordForm.description": "Ce document est protégé. Veuillez entrer votre mot de passe.",
  "passwordForm.ok": "OK",
  "passwordForm.cancel": "Annuler",
  "passwordForm.passwordRequiredError": "Mot de passe requis",
  "passwordForm.invalidPasswordError": "Le mot de passe n’est pas valide",
  "applicationLoader.title": "Chargement",
  "applicationError.title": "Erreur",
  "applicationError.reload": "Recharger",
  "applicationError.defaultMessage": "Une erreur s’est produite",
  "applicationError.invalidLicense": "Licence invalide",
  "unsavedChanges.description": "Voulez-vous sauvegarder les changements effectués sur le document ?",
  "unsavedChanges.save": "Sauvegarder",
  "unsavedChanges.dontSave": "Ne pas sauvegarder",
  "unsavedChanges.cancel": "Annuler",
  "search.inputPlaceholder": "Rechercher dans le document",
  "search.optionCaseSensitive": "Prendre en compte les majuscules et minuscules",
  "search.optionWrap": "Recherche circulaire",
  "search.optionRegularExpression": "Expressions régulières",
  "search.previousMatch": "Correspondance précédente",
  "search.nextMatch": "Correspondance suivante",
  "search.options": "Options",
  "sideNavigation.thumbnails": "Pages",
  "sideNavigation.outline": "Tables des matières",
  "sideNavigation.noOutline": "Pas de table des matières",
  "sideNavigation.annotation": "Annotation",
  "sideNavigation.noAnnotations": "Pas d'annotations",
  "sideNavigation.annotation.page": "Page",
  "sideNavigation.annotation.history": "Historique",
  "rotatePage.clockwise": "Rotation horaire",
  "rotatePage.counterclockwise": "Rotation antihoraire",
  "pageLayoutMode.oneColumn": "Défilement",
  "pageLayoutMode.singlePage": "Affichage d’une page",
  "pageLayoutMode.twoColumnLeft": "Défilement sur deux pages",
  "pageLayoutMode.twoColumnRight": "Défilement sur deux pages droite",
  "pageLayoutMode.twoPageLeft": "Affichage sur deux pages",
  "pageLayoutMode.twoPageRight": "Affichage sur deux pages droite",
  "fitMode.page": "Adapter à la page",
  "fitMode.width": "Adapter à la largeur",
  "fitMode.none": "Pas d’adaptation",
  "toolbar.openDocument": "Ouvrir document",
  "toolbar.closeDocument": "Fermer document",
  "toolbar.print": "Imprimer document",
  "toolbar.saveDocument": "Enregistrer document",
  "toolbar.nextPage": "Page suivante",
  "toolbar.previewsPage": "Page précédente",
  "toolbar.pageOf": "de",
  "toolbar.zoom": "Zoom",
  "toolbar.zoomIn": "Zoom +",
  "toolbar.zoomOut": "Zoom -",
  "toolbar.rotateView": "Pivoter affichage",
  "toolbar.search": "Chercher",
  "toolbar.toggleSidePane": "Basculer volet latéral",
  "toolbar.annotationsMenuButton": "Ajouter annotation",
  "annotText.add": "Note",
  "annotFreeDrawing.add": "Dessin libre",
  "annotFreeDrawing.opacity": "Opacité",
  "annotFreeDrawing.strokeWidth": "Taille du trait",
  "annotFreeDrawing.undo": "Supprimer dernière ligne",
  "annotFreeDrawing.addNew": "Nouveau dessin libre",
  "annotFreeDrawing.deleteLine": "Cliquer pour supprimer des lignes",
  "annotFreeText.add": "Texte",
  "annotFreeText.edit": "Éditer",
  "annotFreeText.fontFamily": "Famille de polices",
  "annotFreeText.fontSize": "Taille de police",
  "annotFreeText.fontColor": "Couleur de police",
  "annotFreeText.bgColor": "Couleur de fond",
  "annotFreeText.borderWidth": "Largeur de bordure",
  "annotFreeText.alignLeft": "Aligner à gauche",
  "annotFreeText.alignCenter": "Aligner au centre",
  "annotFreeText.alignRight": "Aligner à droite",
  "annotFreeText.bold": "Gras",
  "annotFreeText.italic": "Italique",
  "annotFreeText.underline": "Souligner",
  "annotFreeText.lock": "Verrouiller annotation",
  "annotFreeText.unlock": "Déverrouiller annotation",
  "annotFreeText.subjectPlaceholder": "Objet",
  "annotHighlight.add": "Surligner texte",
  "annotHighlight.edit": "Éditer",
  "annotHighlight.highlight": "Surligner",
  "annotHighlight.rectangularHighlight": "Surligner",
  "annotHighlight.underline": "Souligner",
  "annotHighlight.squiggly": "Soulignement ondulé",
  "annotHighlight.strikeOut": "Barrer",
  "annotInk.edit": "Éditer",
  "annotStamp.add": "Tampon",
  "annotStamp.chooseStamp": "Choisir tampon",
  "annotShape.add": "Forme",
  "annotShape.edit": "Éditer",
  "annotShape.addRectangle": "Rectangle",
  "annotShape.addEllipse": "Ellipse",
  "annotShape.strokeColor": "Couleur de trait",
  "annotShape.strokeWidth": "Largeur de trait",
  "annotShape.strokeStyle": "Style de trait",
  "annotShape.bgColor": "Couleur de fond",
  "annotImage.add": "Tampon image",
  "annotPopup.delete": "Supprimer popup",
  "annotPopup.lock": "Verrouiller annotation",
  "annotPopup.unlock": "Déverrouiller annotation",
  "annotPopup.color": "Sélectionner couleur",
  "annotPopup.subjectPlaceholder": "Objet",
  "annotPopup.contentPlaceholder": "Contenu",
  "eraser.begin": "Supprimer les lignes de dessin libre",
  "eraser.deleteFreeDrawingLines": "Cliquer pour supprimer les lignes de dessin libre",
  "eraser.eraserWidth": "Largeur de la gomme",
  "contextbar.rotate": "Pivoter annotation",
  "contextbar.editPopup": "Éditer popup",
  "contextbar.addPopup": "Ajouter popup",
  "contextbar.openPopup": "Ouvrir popup",
  "contextbar.deletePopup": "Supprimer popup",
  "contextbar.lock": "Verrouiller annotation",
  "contextbar.unlock": "Déverrouiller annotation",
  "contextbar.delete": "Supprimer annotation",
  "contextbar.confirmDelete": "Effacer",
  "contextbar.cancelDelete": "Annuler",
  "contextbar.copyText": "Copier texte",
  "contextbar.highlightText": "Surligner le texte sélectionné",
  "contextbar.underlineText": "Souligner le texte sélectionné",
  "contextbar.squigglyText": "Souligner en ondulé le texte sélectionné",
  "contextbar.strikeOutText": "Barrer le texte sélectionné",
  "errors.invalidLicense": "License non valide",
  "stamptext.approved": "APPROUVÉ",
  "stamptext.notApproved": "NON APPROUVÉ",
  "stamptext.draft": "EBAUCHE",
  "stamptext.final": "DOCUMENT FINAL",
  "stamptext.completed": "DOCUMENT TERMINÉ",
  "stamptext.confidential": "CONFIDENTIEL",
  "stamptext.forPublic": "POUR DIVULGATION PUBLIQUE",
  "stamptext.notForPublic": "PAS POUR DIVULGATION PUBLIQUE",
  "stamptext.void": "ANNULÉ",
  "stamptext.forComment": "A COMMENTER",
  "stamptext.preliminaryResults": "RÉSULTATS PRÉLIMINAIRES",
  "stamptext.informationOnly": "POUR INFORMATION",
  "print.title": "Imprimer",
  "print.all": "Toutes les pages",
  "print.current": "Page actuelle",
  "print.range": "Intervalle",
  "print.invalid": "Intervalle invalide",
  "print.print": "Imprimer",
  "print.cancel": "Annuler",
  "border.none": "Pas de bordure"
}
